grkmemory/__init__.py
grkmemory/py.typed
grkmemory/auth/__init__.py
grkmemory/auth/auth.py
grkmemory/auth/cli.py
grkmemory/auth/token_manager.py
grkmemory/core/__init__.py
grkmemory/core/agent.py
grkmemory/core/config.py
grkmemory/core/grkmemory.py
grkmemory/graph/__init__.py
grkmemory/graph/semantic_graph.py
grkmemory/memory/__init__.py
grkmemory/memory/repository.py
grkmemory/utils/__init__.py
grkmemory/utils/embeddings.py
grkmemory/utils/text.py
grkmemory-1.2.1.dist-info/licenses/LICENSE
grkmemory-1.2.1.dist-info/METADATA
grkmemory-1.2.1.dist-info/WHEEL
grkmemory-1.2.1.dist-info/entry_points.txt
grkmemory-1.2.1.dist-info/top_level.txt
grkmemory-1.2.1.dist-info/RECORD
