Metadata-Version: 2.4
Name: grkmemory
Version: 1.2.1
Summary: GRKMemory (Graph Retrieve Knowledge Memory) - A semantic graph-based memory system for AI agents developed by MonkAI team
Author-email: Arthur Vaz <contato@monkai.com.br>
Maintainer-email: Arthur Vaz <contato@monkai.com.br>
License: MIT
Project-URL: Homepage, https://github.com/BeMonkAI/GRKMemory
Project-URL: Documentation, https://github.com/BeMonkAI/GRKMemory#readme
Project-URL: Repository, https://github.com/BeMonkAI/GRKMemory
Project-URL: Issues, https://github.com/BeMonkAI/GRKMemory/issues
Keywords: grkmemory,monkai,ai,agents,memory,semantic-graph,knowledge-retrieval,openai,llm,chatgpt,conversational-ai,machine-learning,toon,token-optimization,serialization
Classifier: Development Status :: 4 - Beta
Classifier: Intended Audience :: Developers
Classifier: License :: OSI Approved :: MIT License
Classifier: Operating System :: OS Independent
Classifier: Programming Language :: Python :: 3
Classifier: Programming Language :: Python :: 3.10
Classifier: Programming Language :: Python :: 3.11
Classifier: Programming Language :: Python :: 3.12
Classifier: Programming Language :: Python :: 3.13
Classifier: Topic :: Scientific/Engineering :: Artificial Intelligence
Classifier: Topic :: Software Development :: Libraries :: Python Modules
Requires-Python: >=3.10
License-File: LICENSE
Requires-Dist: openai>=1.0.0
Requires-Dist: openai-agents>=0.6.0
Requires-Dist: pydantic>=2.0.0
Provides-Extra: dev
Requires-Dist: pytest>=7.0.0; extra == "dev"
Requires-Dist: pytest-asyncio>=0.21.0; extra == "dev"
Requires-Dist: black>=23.0.0; extra == "dev"
Requires-Dist: isort>=5.12.0; extra == "dev"
Requires-Dist: mypy>=1.0.0; extra == "dev"
Provides-Extra: embeddings
Requires-Dist: tiktoken>=0.5.0; extra == "embeddings"
Provides-Extra: toon
Requires-Dist: toon_format>=0.9.0; extra == "toon"
Provides-Extra: all
Requires-Dist: grkmemory[dev,embeddings,toon]; extra == "all"
Dynamic: license-file
